pychatml/__init__.py
pychatml/abstract.py
pychatml/alpaca_converter.py
pychatml/anthropic_converter.py
pychatml/llama2_converter.py
pychatml/vicuna_v1_1_converter.py
pychatml/alpaca/__init__.py
pychatml/alpaca/alpaca.py
pychatml/anthropic/__init__.py
pychatml/anthropic/anthropic.py
pychatml/llama2/__init__.py
pychatml/llama2/llama2.py
tests/__init__.py
tests/test_alpaca.py
tests/test_anthropic.py
tests/test_llama2.py
tests/test_vicuna_v1_1.py
pychatml-0.0.6.dist-info/LICENSE
pychatml-0.0.6.dist-info/METADATA
pychatml-0.0.6.dist-info/WHEEL
pychatml-0.0.6.dist-info/top_level.txt
pychatml-0.0.6.dist-info/RECORD
