Metadata-Version: 2.1
Name: pychatml
Version: 0.0.6
Summary: A package for converting chat messages to and from ChatML format
Author: Radiant AI
Author-email: jakob@radiantai.com
Classifier: Development Status :: 3 - Alpha
Classifier: Intended Audience :: Developers
Classifier: License :: OSI Approved :: MIT License
Classifier: Programming Language :: Python :: 3
Classifier: Programming Language :: Python :: 3.6
Classifier: Programming Language :: Python :: 3.7
Classifier: Programming Language :: Python :: 3.8
License-File: LICENSE
Requires-Dist: anthropic
Requires-Dist: openai
